odoo/addons/mrp_bom_tracking/README.rst
odoo/addons/mrp_bom_tracking/__init__.py
odoo/addons/mrp_bom_tracking/__manifest__.py
odoo/addons/mrp_bom_tracking/i18n/de.po
odoo/addons/mrp_bom_tracking/i18n/es.po
odoo/addons/mrp_bom_tracking/i18n/it.po
odoo/addons/mrp_bom_tracking/i18n/mrp_bom_tracking.pot
odoo/addons/mrp_bom_tracking/i18n/nl.po
odoo/addons/mrp_bom_tracking/i18n/nl_NL.po
odoo/addons/mrp_bom_tracking/i18n/pt_BR.po
odoo/addons/mrp_bom_tracking/i18n/tr.po
odoo/addons/mrp_bom_tracking/models/__init__.py
odoo/addons/mrp_bom_tracking/models/mrp_bom.py
odoo/addons/mrp_bom_tracking/readme/CONTRIBUTORS.md
odoo/addons/mrp_bom_tracking/readme/DESCRIPTION.md
odoo/addons/mrp_bom_tracking/static/description/icon.png
odoo/addons/mrp_bom_tracking/static/description/index.html
odoo/addons/mrp_bom_tracking/tests/__init__.py
odoo/addons/mrp_bom_tracking/tests/test_mrp_bom_tracking.py
odoo/addons/mrp_bom_tracking/views/bom_template.xml
odoo_addon_mrp_bom_tracking-19.0.1.0.0.2.dist-info/METADATA
odoo_addon_mrp_bom_tracking-19.0.1.0.0.2.dist-info/WHEEL
odoo_addon_mrp_bom_tracking-19.0.1.0.0.2.dist-info/top_level.txt
odoo_addon_mrp_bom_tracking-19.0.1.0.0.2.dist-info/RECORD
