Metadata-Version: 2.1
Name: odoo-addon-mrp_bom_tracking
Version: 19.0.1.0.0.2
Requires-Dist: odoo==19.0.*
Summary: Logs any change to a BoM in the chatter
Home-page: https://github.com/OCA/manufacture
License: LGPL-3
Author: ForgeFlow, Odoo Community Association (OCA)
Author-email: support@odoo-community.org
Classifier: Programming Language :: Python
Classifier: Framework :: Odoo
Classifier: Framework :: Odoo :: 19.0
Classifier: License :: OSI Approved :: GNU Lesser General Public License v3 (LGPLv3)
Classifier: Development Status :: 5 - Production/Stable
